rule34Py/__init__.py
rule34Py/api_urls.py
rule34Py/autocomplete_tag.py
rule34Py/html.py
rule34Py/icame.py
rule34Py/pool.py
rule34Py/post.py
rule34Py/post_comment.py
rule34Py/rule34.py
rule34Py/toptag.py
rule34py-4.0.2.dist-info/METADATA
rule34py-4.0.2.dist-info/WHEEL
rule34py-4.0.2.dist-info/licenses/LICENSE
rule34py-4.0.2.dist-info/licenses/NOTICE.md
rule34py-4.0.2.dist-info/RECORD
