Metadata-Version: 2.4
Name: rule34Py
Version: 4.0.2
Summary: API wrapper for rule34.xxx
License: GPL-3.0-only
License-File: LICENSE
License-File: NOTICE.md
Keywords: adult,api-client,nsfw,rule34-pi,rule34.xxx
Author: b3yc0d3
Author-email: b3yc0d3@gmail.com
Maintainer: b3yc0d3
Maintainer-email: b3yc0d3@gmail.com
Requires-Python: >=3.9, <4.0
Classifier: Development Status :: 4 - Beta
Classifier: License :: OSI Approved :: GNU General Public License v3 (GPLv3)
Classifier: Operating System :: OS Independent
Classifier: Programming Language :: Python :: 3
Classifier: Programming Language :: Python :: 3.9
Classifier: Programming Language :: Python :: 3.10
Classifier: Programming Language :: Python :: 3.11
Classifier: Programming Language :: Python :: 3.12
Classifier: Programming Language :: Python :: 3.13
Classifier: Programming Language :: Python :: 3.14
Requires-Dist: beautifulsoup4
Requires-Dist: lxml
Requires-Dist: requests
Requires-Dist: requests-ratelimiter
Project-URL: Documentation, https://b3yc0d3.github.io/rule34Py/
Project-URL: Issues, https://github.com/b3yc0d3/rule34Py/issues
Project-URL: Repository, https://github.com/b3yc0d3/rule34Py
